planetcantile/__init__.py
planetcantile/app.py
planetcantile/debugalgo.py
planetcantile/defaults.py
planetcantile/topoalgo.py
planetcantile/data/__init__.py
planetcantile/data/generate.py
planetcantile/data/generate_proj4js.py
planetcantile/data/v4/52EuropaEquidistantCylindricalSphere.json
planetcantile/data/v4/52EuropaEquidistantCylindricalSphereCoalesced.json
planetcantile/data/v4/52EuropaGeographicSphere.json
planetcantile/data/v4/52EuropaGeographicSphereCoalesced.json
planetcantile/data/v4/52EuropaMercatorSphere.json
planetcantile/data/v4/52EuropaNorthPolarSphere.json
planetcantile/data/v4/52EuropaSouthPolarSphere.json
planetcantile/data/v4/52EuropaWebMercatorSphere.json
planetcantile/data/v4/AdrasteaEquidistantCylindricalSphere.json
planetcantile/data/v4/AdrasteaEquidistantCylindricalSphereCoalesced.json
planetcantile/data/v4/AdrasteaGeographicSphere.json
planetcantile/data/v4/AdrasteaGeographicSphereCoalesced.json
planetcantile/data/v4/AdrasteaMercatorSphere.json
planetcantile/data/v4/AdrasteaNorthPolarSphere.json
planetcantile/data/v4/AdrasteaSouthPolarSphere.json
planetcantile/data/v4/AdrasteaWebMercatorSphere.json
planetcantile/data/v4/AegaeonEquidistantCylindricalSphere.json
planetcantile/data/v4/AegaeonEquidistantCylindricalSphereCoalesced.json
planetcantile/data/v4/AegaeonGeographicSphere.json
planetcantile/data/v4/AegaeonGeographicSphereCoalesced.json
planetcantile/data/v4/AegaeonMercatorSphere.json
planetcantile/data/v4/AegaeonNorthPolarSphere.json
planetcantile/data/v4/AegaeonSouthPolarSphere.json
planetcantile/data/v4/AegaeonWebMercatorSphere.json
planetcantile/data/v4/AmaltheaEquidistantCylindricalSphere.json
planetcantile/data/v4/AmaltheaEquidistantCylindricalSphereCoalesced.json
planetcantile/data/v4/AmaltheaGeographicSphere.json
planetcantile/data/v4/AmaltheaGeographicSphereCoalesced.json
planetcantile/data/v4/AmaltheaMercatorSphere.json
planetcantile/data/v4/AmaltheaNorthPolarSphere.json
planetcantile/data/v4/AmaltheaSouthPolarSphere.json
planetcantile-0.6.0.dist-info/licenses/LICENSE
planetcantile-0.6.0.dist-info/METADATA
planetcantile-0.6.0.dist-info/WHEEL
planetcantile-0.6.0.dist-info/top_level.txt
planetcantile-0.6.0.dist-info/RECORD
