Metadata-Version: 2.4
Name: planetcantile
Version: 0.6.0
Summary: TMS tilesets for Planets
Author-email: Andrew Annex <ama6fy@virginia.edu>
License: BSD License
Project-URL: Repository, https://github.com/AndrewAnnex/planetcantile
Keywords: morecantile,TMS,TileMatrixSet,GIS
Classifier: Development Status :: 3 - Alpha
Classifier: Programming Language :: Python :: 3.10
Classifier: Programming Language :: Python :: 3.11
Classifier: Programming Language :: Python :: 3.12
Classifier: Topic :: Scientific/Engineering :: GIS
Classifier: Intended Audience :: Science/Research
Classifier: License :: OSI Approved :: BSD License
Requires-Python: >=3.10
License-File: LICENSE
Requires-Dist: morecantile>=6.1.0
Requires-Dist: click>=8.1.3
Requires-Dist: pillow
Requires-Dist: pyproj>=3.6.1
Requires-Dist: numpy
Provides-Extra: dev
Requires-Dist: spiceypy; extra == "dev"
Requires-Dist: titiler.application>=0.19.0; extra == "dev"
Requires-Dist: pillow; extra == "dev"
Requires-Dist: pytest>=8.3.0; extra == "dev"
Requires-Dist: planet-crs-registry-client; extra == "dev"
Provides-Extra: app
Requires-Dist: titiler.application>=0.19.0; extra == "app"
Requires-Dist: rio_tiler>=7.2.0; extra == "app"
Requires-Dist: starlette; extra == "app"
Requires-Dist: pillow; extra == "app"
Requires-Dist: fastapi; extra == "app"
Requires-Dist: uvicorn; extra == "app"
Dynamic: license-file
